<?xml version="1.0" encoding="windows-1252"?>
<XMI xmi.version="1.1" xmlns:UML="omg.org/UML1.3">
	<XMI.header>
		<XMI.documentation>
			<XMI.exporter>Enterprise Architect</XMI.exporter>
			<XMI.exporterVersion>2.5</XMI.exporterVersion>
		</XMI.documentation>
	</XMI.header>
	<XMI.content>
		<UML:Model name="EA Model" xmi.id="MX_EAID_2F66B7FC_EF92_4ffb_84A7_290E92AF2A88">
			<UML:Namespace.ownedElement>
				<UML:Class name="EARootClass" xmi.id="EAID_11111111_5487_4080_A7F4_41526CB0AA00" isRoot="true" isLeaf="false" isAbstract="false"/>
				<UML:Package name="Collectionxxx" xmi.id="EAPK_2F66B7FC_EF92_4ffb_84A7_290E92AF2A88" isRoot="false" isLeaf="false" isAbstract="false" visibility="public">
					<UML:ModelElement.stereotype>
						<UML:Stereotype xmi.idref="EAID_855FC283_DEF2_4d50_AA44_608E3F57568D"/>
					</UML:ModelElement.stereotype>
					<UML:ModelElement.taggedValue>
						<UML:TaggedValue tag="documentation" value="The GeoSciML Collection package contains facade classes that facilitate the structuring of WFS response documents and other application uses."/>
						<UML:TaggedValue tag="parent" value="EAPK_FB372980_4B14_4301_87EA_545AC68BE474"/>
						<UML:TaggedValue tag="created" value="2011-06-17 15:18:52"/>
						<UML:TaggedValue tag="modified" value="2014-06-30 15:03:48"/>
						<UML:TaggedValue tag="iscontrolled" value="TRUE"/>
						<UML:TaggedValue tag="xmlpath" value="collection\gsml4Collection.xml"/>
						<UML:TaggedValue tag="lastloaddate" value="2014-06-30 14:49:36"/>
						<UML:TaggedValue tag="lastsavedate" value="2011-06-20 15:10:24"/>
						<UML:TaggedValue tag="version" value="4.0.0"/>
						<UML:TaggedValue tag="isprotected" value="FALSE"/>
						<UML:TaggedValue tag="usedtd" value="FALSE"/>
						<UML:TaggedValue tag="xmiver" value="Enterprise Architect XMI/UML 1.3"/>
						<UML:TaggedValue tag="logxml" value="FALSE"/>
						<UML:TaggedValue tag="tpos" value="8"/>
						<UML:TaggedValue tag="packageFlags" value="Recurse=0;VCCFG=GeoSciML4;CRC=0;"/>
						<UML:TaggedValue tag="batchsave" value="0"/>
						<UML:TaggedValue tag="batchload" value="0"/>
						<UML:TaggedValue tag="phase" value="1.0"/>
						<UML:TaggedValue tag="status" value="Proposed"/>
						<UML:TaggedValue tag="author" value="GeoSciML SWG"/>
						<UML:TaggedValue tag="complexity" value="1"/>
						<UML:TaggedValue tag="stereotype" value="Leaf"/>
						<UML:TaggedValue tag="ea_stype" value="Public"/>
						<UML:TaggedValue tag="tpos" value="8"/>
						<UML:TaggedValue tag="gentype" value="Java"/>
					</UML:ModelElement.taggedValue>
					<UML:Namespace.ownedElement>
						<UML:Dependency client="EAPK_2F66B7FC_EF92_4ffb_84A7_290E92AF2A88" supplier="EAPK_FB372980_4B14_4301_87EA_545AC68BE474" xmi.id="EAID_04F9EA60_4429_48aa_A6F5_B61F9687966D" visibility="public">
							<UML:ModelElement.stereotype>
								<UML:Stereotype name="import"/>
							</UML:ModelElement.stereotype>
							<UML:ModelElement.taggedValue>
								<UML:TaggedValue tag="documentation" value="Created by HollowWorld Plugin"/>
								<UML:TaggedValue tag="style" value="3"/>
								<UML:TaggedValue tag="ea_type" value="Dependency"/>
								<UML:TaggedValue tag="direction" value="Source -&gt; Destination"/>
								<UML:TaggedValue tag="linemode" value="3"/>
								<UML:TaggedValue tag="linecolor" value="-1"/>
								<UML:TaggedValue tag="linewidth" value="0"/>
								<UML:TaggedValue tag="seqno" value="0"/>
								<UML:TaggedValue tag="stereotype" value="import"/>
								<UML:TaggedValue tag="headStyle" value="0"/>
								<UML:TaggedValue tag="lineStyle" value="0"/>
								<UML:TaggedValue tag="conditional" value=" &#xA;«Import»"/>
								<UML:TaggedValue tag="ea_localid" value="24272"/>
								<UML:TaggedValue tag="ea_sourceName" value="Collectionxxx"/>
								<UML:TaggedValue tag="ea_targetName" value="GeoSciMLBasic"/>
								<UML:TaggedValue tag="ea_sourceType" value="Package"/>
								<UML:TaggedValue tag="ea_targetType" value="Package"/>
								<UML:TaggedValue tag="ea_sourceID" value="19694"/>
								<UML:TaggedValue tag="ea_targetID" value="19693"/>
								<UML:TaggedValue tag="src_visibility" value="Public"/>
								<UML:TaggedValue tag="src_aggregation" value="0"/>
								<UML:TaggedValue tag="src_isOrdered" value="false"/>
								<UML:TaggedValue tag="src_isNavigable" value="false"/>
								<UML:TaggedValue tag="src_style" value="Owned=0;Navigable=Non-Navigable;"/>
								<UML:TaggedValue tag="dst_visibility" value="Public"/>
								<UML:TaggedValue tag="dst_aggregation" value="0"/>
								<UML:TaggedValue tag="dst_isOrdered" value="false"/>
								<UML:TaggedValue tag="dst_isNavigable" value="false"/>
								<UML:TaggedValue tag="dst_style" value="Owned=0;Navigable=Navigable;"/>
								<UML:TaggedValue tag="virtualInheritance" value="0"/>
								<UML:TaggedValue tag="mb" value=" &#xA;«import»"/>
							</UML:ModelElement.taggedValue>
						</UML:Dependency>
					</UML:Namespace.ownedElement>
				</UML:Package>
				<UML:Stereotype xmi.id="EAID_855FC283_DEF2_4d50_AA44_608E3F57568D" name="Leaf" isRoot="false" isLeaf="false" isAbstract="false">
					<UML:Stereotype.baseClass>Package</UML:Stereotype.baseClass>
				</UML:Stereotype>
			</UML:Namespace.ownedElement>
		</UML:Model>
		<UML:TaggedValue tag="xsdDocument" xmi.id="EAID_6E79370E_77F4_9777_AF15_D1686C1DA891" value="#NOTES#Description: Name of an XML Schema document to create representing the content of this package&#xA;" modelElement="MX_EAID_2F66B7FC_EF92_4ffb_84A7_290E92AF2A88"/>
		<UML:TaggedValue tag="xsdEncodingRule" xmi.id="EAID_BCD3CBEE_83B4_4283_A973_9AED1CD0F912" value="iso19136_2007#NOTES#Values: iso19136_2007,iso19139_2007,iso19136_2007_INSPIRE_Extensions&#xA;Default: iso19136_2007&#xA;" modelElement="MX_EAID_2F66B7FC_EF92_4ffb_84A7_290E92AF2A88"/>
		<UML:DiagramElement geometry="Left=31;Top=267;Right=169;Bottom=347;" subject="EAID_2F66B7FC_EF92_4ffb_84A7_290E92AF2A88" seqno="1" style="DUID=4D0C4069;">
			<UML:ModelElement.taggedValue>
				<UML:TaggedValue tag="diagram_guid" value="EAID_D00BC0E3_483C_49ab_B282_C1F9D8BA057A"/>
			</UML:ModelElement.taggedValue>
		</UML:DiagramElement>
		<UML:DiagramElement geometry="Left=431;Top=299;Right=569;Bottom=379;" subject="EAID_2F66B7FC_EF92_4ffb_84A7_290E92AF2A88" seqno="7" style="DUID=4A1D8DF7;NSL=0;BCol=-1;BFol=-1;LCol=-1;LWth=-1;fontsz=0;bold=0;italic=0;ul=0;charset=0;pitch=0;">
			<UML:ModelElement.taggedValue>
				<UML:TaggedValue tag="diagram_guid" value="EAID_4157095F_4BCC_4734_8DF3_434FED337892"/>
			</UML:ModelElement.taggedValue>
		</UML:DiagramElement>
		<UML:DiagramElement geometry="SX=0;SY=0;EX=0;EY=0;" subject="EAID_04F9EA60_4429_48aa_A6F5_B61F9687966D" style=";">
			<UML:ModelElement.taggedValue>
				<UML:TaggedValue tag="diagram_guid" value="EAID_D00BC0E3_483C_49ab_B282_C1F9D8BA057A"/>
				<UML:TaggedValue tag="hidden" value="0"/>
			</UML:ModelElement.taggedValue>
		</UML:DiagramElement>
		<UML:DiagramElement geometry="SX=0;SY=0;EX=0;EY=0;" subject="EAID_04F9EA60_4429_48aa_A6F5_B61F9687966D">
			<UML:ModelElement.taggedValue>
				<UML:TaggedValue tag="diagram_guid" value="EAID_4157095F_4BCC_4734_8DF3_434FED337892"/>
				<UML:TaggedValue tag="hidden" value="0"/>
			</UML:ModelElement.taggedValue>
		</UML:DiagramElement>
	</XMI.content>
	<XMI.difference/>
	<XMI.extensions xmi.extender="Enterprise Architect 2.5">
		<EAStub xmi.id="EAPK_FB372980_4B14_4301_87EA_545AC68BE474" name="GeoSciMLBasic" UMLType="Package"/>
	</XMI.extensions>
</XMI>
