<?xml version="1.0" encoding="UTF-8"?>
<mapping
	xmlns:xsd="http://www.w3.org/2001/XMLSchema"
	xmlns:xsi="http://www.w3.org/2001/XMLSchema-instance"
	xmlns:gsml="urn:cgi:xmlns:CGI:GeoSciML:2.0"
	xmlns="urn:x-auscope:xmlns:CSIRO:FullMoon:package-class-map:2.0"
	xsi:schemaLocation="urn:x-auscope:xmlns:CSIRO:FullMoon:package-class-map:2.0 http://projects.arcs.org.au/svn/fullmoon/trunk/resources/dependency-util/package-class-map.xsd"
	id="ClassMap_core_GeoSciML_V2.xml">
	<description>Provides a mapping of classes from the core module of GeoSciML to elements from GeoSciML XML Schema Version 2.0.</description>
	<imports>
		<schema prefix="gsml" namespace="urn:cgi:xmlns:CGI:GeoSciML:2.0" schemaLocation="http://www.geosciml.org/geosciml/2.0/xsd/geosciml.xsd" />
	</imports>
	<entry>
		<umlClass>ControlledConcept</umlClass>
		<umlStereotype>Type</umlStereotype>
		<gmlObjectElement>gsml:ControlledConcept</gmlObjectElement>
		<gmlType>gsml:ControlledConceptType</gmlType>
		<gmlPropertyType>gsml:ControlledConceptPropertyType</gmlPropertyType>
	</entry>
	<entry>
		<umlClass>DescriptionPurpose</umlClass>
		<umlStereotype>CodeList</umlStereotype>
		<gmlObjectElement xsi:nil="true"/>
		<gmlType xsi:nil="true"/>
		<gmlPropertyType>gsml:DescriptionPurposeType</gmlPropertyType>
	</entry>
	<entry>
		<umlClass>GeologicFeature</umlClass>
		<gmlObjectElement>gsml:GeologicFeature</gmlObjectElement>
		<gmlType>gsml:GeologicFeatureType</gmlType>
		<gmlPropertyType>gsml:GeologicFeaturePropertyType</gmlPropertyType>
	</entry>
	<entry>
		<umlClass>GeologicFeatureRelation</umlClass>
		<gmlObjectElement>gsml:GeologicFeatureRelation</gmlObjectElement>
		<gmlType>gsml:GeologicFeatureRelationType</gmlType>
		<gmlPropertyType>gsml:GeologicFeatureRelationPropertyType</gmlPropertyType>
	</entry>
	<entry>
		<umlClass>GeologicRelation</umlClass>
		<gmlObjectElement>gsml:GeologicRelation</gmlObjectElement>
		<gmlType>gsml:GeologicRelationType</gmlType>
		<gmlPropertyType>gsml:GeologicRelationPropertyType</gmlPropertyType>
	</entry>
	<entry>
		<umlClass>GeologicVocabulary</umlClass>
		<umlStereotype>Type</umlStereotype>
		<gmlObjectElement>gsml:GeologicVocabulary</gmlObjectElement>
		<gmlType>gsml:GeologicVocabularyType</gmlType>
		<gmlPropertyType>gsml:GeologicVocabularyPropertyType</gmlPropertyType>
	</entry>
	<entry>
		<umlClass>GSML</umlClass>
		<umlStereotype>FeatureType</umlStereotype>
		<gmlObjectElement>gsml:GSML</gmlObjectElement>
		<gmlType>gsml:GSMLType</gmlType>
		<gmlPropertyType>gsml:GSMLPropertyType</gmlPropertyType>
	</entry>
	<entry>
		<umlClass>GSMLitem</umlClass>
		<umlStereotype>Union</umlStereotype>
		<gmlObjectElement xsi:nil="true"/>
		<gmlType xsi:nil="true"/>
		<gmlPropertyType>gsml:GSMLitemPropertyType</gmlPropertyType>
	</entry>
	<entry>
		<umlClass>MappedFeature</umlClass>
		<gmlObjectElement>gsml:MappedFeature</gmlObjectElement>
		<gmlType>gsml:MappedFeatureType</gmlType>
		<gmlPropertyType>gsml:MappedFeaturePropertyType</gmlPropertyType>
	</entry>
	<entry>
		<umlClass>StratigraphicLexicon</umlClass>
		<umlStereotype>Type</umlStereotype>
		<gmlObjectElement>gsml:StratigraphicLexicon</gmlObjectElement>
		<gmlType>gsml:StratigraphicLexiconType</gmlType>
		<gmlPropertyType>gsml:StratigraphicLexiconPropertyType</gmlPropertyType>
	</entry>
	<entry>
		<umlClass>VocabRelation</umlClass>
		<umlStereotype>Type</umlStereotype>
		<gmlObjectElement>gsml:VocabRelation</gmlObjectElement>
		<gmlType>gsml:VocabRelationType</gmlType>
		<gmlPropertyType>gsml:VocabRelationPropertyType</gmlPropertyType>
	</entry>
</mapping>